retrieval/__init__.py
retrieval/wikipedia.py
openchatkit-0.0.1.dev0.dist-info/LICENSE
openchatkit-0.0.1.dev0.dist-info/METADATA
openchatkit-0.0.1.dev0.dist-info/WHEEL
openchatkit-0.0.1.dev0.dist-info/top_level.txt
openchatkit-0.0.1.dev0.dist-info/RECORD
