Metadata-Version: 2.1
Name: openchatkit
Version: 0.0.1.dev0
Summary: OpenChatKit - a powerful, open-source base to create both specialized and general purpose chatbots
Home-page: https://github.com/shadowwalker2718/OpenChatKit
Author: Shadow Walker
Author-email: shadowwalker2718@gmail.com
License: UNKNOWN
Keywords: OpenChatKit
Platform: UNKNOWN
Classifier: Programming Language :: Python :: 3
Classifier: Programming Language :: Python :: 3.6
Classifier: Programming Language :: Python :: 3.7
Classifier: Programming Language :: Python :: 3.8
Classifier: Programming Language :: Python :: 3.9
Classifier: Programming Language :: Python :: 3.10
Classifier: Programming Language :: Python :: 3.11
License-File: LICENSE
Requires-Dist: datasets (~=2.10.1)
Requires-Dist: loguru (~=0.6.0)
Requires-Dist: netifaces (~=0.11.0)
Requires-Dist: transformers (~=4.21.1)
Requires-Dist: wandb (~=0.13.10)
Requires-Dist: zstandard (~=0.20.0)
Requires-Dist: torch
Requires-Dist: cupy (~=10.4.0)
Requires-Dist: faiss-gpu (~=1.7.2)
Requires-Dist: fastparquet (~=0.5.0)
Requires-Dist: pip (~=22.3.1)
Requires-Dist: pyarrow (~=8.0.0)
Requires-Dist: torchaudio (~=0.13.1)
Requires-Dist: torchvision (~=0.14.1)
